sine.path-0.1.2-py2.7-nspkg.pth
sine/path/__init__.py
sine/path/__version__.py
sine/path/core.py
sine/path/tests.py
sine.path-0.1.2.dist-info/DESCRIPTION.rst
sine.path-0.1.2.dist-info/METADATA
sine.path-0.1.2.dist-info/RECORD
sine.path-0.1.2.dist-info/WHEEL
sine.path-0.1.2.dist-info/metadata.json
sine.path-0.1.2.dist-info/namespace_packages.txt
sine.path-0.1.2.dist-info/top_level.txt
